{
  "domain": "Artificial intelligence ",
  "timestamp": "20250506_091848",
  "api_provider": "",
  "tier_a_model": "sonar",
  "tier_b_model": "sonar-reasoning",
  "max_labels": 9,
  "min_labels": 8,
  "deny_list": [
    "Partnership",
    "Funding",
    "Hiring"
  ],
  "approved_labels": [
    "Model-Launch",
    "Algorithm-Breakthrough",
    "Ethical-Controversy",
    "Regulatory-Approval",
    "System-Outage",
    "Data-Breach",
    "Benchmark-Achievement",
    "Generative-Release",
    "Framework-Withdrawal"
  ],
  "rejected_labels": {}
}